openframe_criteria_set_protocol/__init__.py
openframe_criteria_set_protocol/v1/__init__.py
openframe_criteria_set_protocol/v1/errors.py
openframe_criteria_set_protocol/v1/schemas.py
openframe_criteria_set_protocol/v1/services.py
openframe_criteria_set_protocol/v1/types.py
openframe_criteria_set_protocol/v1/utils.py
openframe_criteria_set_protocol-2.7.0.dist-info/licenses/LICENSE
tests/__init__.py
tests/v1/__init__.py
tests/v1/test_schemas.py
tests/v1/test_types.py
openframe_criteria_set_protocol-2.7.0.dist-info/METADATA
openframe_criteria_set_protocol-2.7.0.dist-info/WHEEL
openframe_criteria_set_protocol-2.7.0.dist-info/top_level.txt
openframe_criteria_set_protocol-2.7.0.dist-info/RECORD
