Metadata-Version: 2.4
Name: openframe-criteria-set-protocol
Version: 2.7.0
Summary: A protocol and tools for defining and working with criteria sets
Author: Andrés Angulo <aa@openframe.org>
Author-email: Andrés Angulo <aa@openframe.org>
Project-URL: Homepage, https://github.com/openframe-org/criteria-set-protocol
Project-URL: Bug Tracker, https://github.com/openframe-org/criteria-set-protocol/issues
Classifier: Programming Language :: Python :: 3
Classifier: License :: OSI Approved :: MIT License
Classifier: Operating System :: OS Independent
Requires-Python: >=3.10
License-File: LICENSE
Requires-Dist: marshmallow
Dynamic: author
Dynamic: license-file
